usadata/__init__.py
usadata/analysis.py
usadata/cleaning.py
usadata/data/MappingAmerica_Education.xlsx
usadata/data/MappingAmerica_Environment.xlsx
usadata/data/MappingAmerica_HDI.xlsx
usadata/data/MappingAmerica_Housing.xlsx
usadata/data/States_Data.csv
usadata/data/US_Locations.csv
usadata/data/US_Locations_PM25_With_Averages.csv
usadata/data/US_Locations_Sampled.csv
usadata/data/US_Locations_Sampled_with_PM25.csv
usadata/data/final_data_set.csv
usadata/streamlit_app.py
usadata-0.1.0.dist-info/WHEEL
usadata-0.1.0.dist-info/entry_points.txt
usadata-0.1.0.dist-info/METADATA
usadata-0.1.0.dist-info/RECORD
