Metadata-Version: 2.3
Name: usadata
Version: 0.1.0
Summary: This package provides data cleaning and visualization tools for US statistics datasets.
Author: Rebekah Jensen, Noah Champagne
License: MIT
Classifier: Programming Language :: Python :: 3
Classifier: Operating System :: OS Independent
Requires-Dist: numpy>=2.3.5
Requires-Dist: pandas>=2.3.3
Requires-Dist: scipy
Requires-Dist: statsmodels
Requires-Dist: plotly
Requires-Dist: streamlit>=1.40.0
Requires-Dist: us
Requires-Dist: requests
Requires-Dist: httpx
Requires-Dist: geopandas
Requires-Dist: plotly
Requires-Python: >=3.11
